MANIFEST.in
README.rst
setup.py
config/jarmanifest.cfg
jarmanifest/__init__.py
jarmanifest/archives.py
jarmanifest/configuration.py
jarmanifest/log.py
jarmanifest/manifest.py
jarmanifest.egg-info/PKG-INFO
jarmanifest.egg-info/SOURCES.txt
jarmanifest.egg-info/dependency_links.txt
jarmanifest.egg-info/top_level.txt