Metadata-Version: 1.1
Name: jarmanifest
Version: 1.0.14
Summary: Tool for parsing Java Manifest files
Home-page: https://github.com/RedHatProductSecurity/JarManifest
Author: Red Hat
Author-email: jshepher@redhat.com
License: GPLv3
Keywords: java dependencies metadata
Platform: UNKNOWN
Classifier: Development Status :: 5 - Production/Stable
Classifier: Intended Audience :: Developers
Classifier: Topic :: Software Development :: Libraries :: Java Libraries
Classifier: License :: OSI Approved :: GNU General Public License v3 or later (GPLv3+)
Classifier: Programming Language :: Python :: 3
Classifier: Programming Language :: Python :: 3.2
Classifier: Programming Language :: Python :: 3.3
Classifier: Programming Language :: Python :: 3.4
